setup.py
emmp_distributions/Binomialdistribution.py
emmp_distributions/Gaussiandistribution.py
emmp_distributions/Generaldistribution.py
emmp_distributions/__init__.py
emmp_distributions.egg-info/PKG-INFO
emmp_distributions.egg-info/SOURCES.txt
emmp_distributions.egg-info/dependency_links.txt
emmp_distributions.egg-info/not-zip-safe
emmp_distributions.egg-info/top_level.txt