Metadata-Version: 1.0
Name: emmp-distributions
Version: 0.1
Summary: Gaussian distributions
Home-page: UNKNOWN
Author: Emily Madrigal
Author-email: emily.mape.98@gmail.com
License: UNKNOWN
Platform: UNKNOWN
